[
	{
		"name": null,
		"coords": [131,228,12],
		"noteURL":"http://i.imgur.com/1p8Y7eP.png"
	},
	{
		"name": null,
		"coords": [703,440,9],
		"noteURL":"http://i.imgur.com/1p8Y7eP.png"
	},
	{
		"name": null,
		"coords": [599,352,9],
		"noteURL":"http://i.imgur.com/1p8Y7eP.png"
	},
	{
		"name": null,
		"coords": [511,175,8],
		"noteURL":"http://i.imgur.com/1p8Y7eP.png"
	},
	{
		"name": null,
		"coords": [173,440,8],
		"noteURL":"http://i.imgur.com/1p8Y7eP.png"
	},
	{
		"name": null,
		"coords": [615,544,8],
		"noteURL":"http://i.imgur.com/1p8Y7eP.png"
	},
	{
		"name": null,
		"coords": [794,765,8],
		"noteURL":"http://i.imgur.com/1p8Y7eP.png"
	},
	{
		"name": null,
		"coords": [63,789,8],
		"noteURL":"http://i.imgur.com/1p8Y7eP.png"
	},
	{
		"name": null,
		"coords": [76,942,8],
		"noteURL":"http://i.imgur.com/1p8Y7eP.png"
	},
	{
		"name": null,
		"coords": [262,409,8],
		"noteURL":"http://i.imgur.com/1p8Y7eP.png"
	},
	{
		"name": null,
		"coords": [347,427,8],
		"noteURL":"http://i.imgur.com/1p8Y7eP.png"
	},
	{
		"name": null,
		"coords": [583,63,8],
		"noteURL":"http://i.imgur.com/1p8Y7eP.png"
	},
	{
		"name": null,
		"coords": [877,487,8],
		"noteURL":"http://i.imgur.com/1p8Y7eP.png"
	},
	{
		"name": null,
		"coords": [147,847,8],
		"noteURL":"http://i.imgur.com/1p8Y7eP.png"
	},
	{
		"name": null,
		"coords": [645,145,8],
		"noteURL":"http://i.imgur.com/1p8Y7eP.png"
	},
	{
		"name": null,
		"coords": [162,737,8],
		"noteURL":"http://i.imgur.com/1p8Y7eP.png"
	},
	{
		"name": null,
		"coords": [104,53,7],
		"noteURL":"http://i.imgur.com/1p8Y7eP.png"
	},
	{
		"name": null,
		"coords": [287,228,7],
		"noteURL":"http://i.imgur.com/1p8Y7eP.png"
	},
	{
		"name": null,
		"coords": [182,751,7],
		"noteURL":"http://i.imgur.com/1p8Y7eP.png"
	},
	{
		"name": null,
		"coords": [360,155,7],
		"noteURL":"http://i.imgur.com/1p8Y7eP.png"
	},
	{
		"name": null,
		"coords": [737,767,7],
		"noteURL":"http://i.imgur.com/1p8Y7eP.png"
	},
	{
		"name": null,
		"coords": [294,142,7],
		"noteURL":"http://i.imgur.com/1p8Y7eP.png"
	},
	{
		"name": null,
		"coords": [768,794,7],
		"noteURL":"http://i.imgur.com/1p8Y7eP.png"
	},
	{
		"name": null,
		"coords": [392,598,7],
		"noteURL":"http://i.imgur.com/1p8Y7eP.png"
	},
	{
		"name": null,
		"coords": [604,583,6],
		"noteURL":"http://i.imgur.com/1p8Y7eP.png"
	},
	{
		"name": null,
		"coords": [665,92,6],
		"noteURL":"http://i.imgur.com/1p8Y7eP.png"
	},
	{
		"name": null,
		"coords": [639,431,6],
		"noteURL":"http://i.imgur.com/1p8Y7eP.png"
	},
	{
		"name": null,
		"coords": [445,363,6],
		"noteURL":"http://i.imgur.com/1p8Y7eP.png"
	},
	{
		"name": null,
		"coords": [565,657,6],
		"noteURL":"http://i.imgur.com/1p8Y7eP.png"
	},
	{
		"name": null,
		"coords": [272,682,6],
		"noteURL":"http://i.imgur.com/1p8Y7eP.png"
	},
	{
		"name": null,
		"coords": [239,908,6],
		"noteURL":"http://i.imgur.com/1p8Y7eP.png"
	},
	{
		"name": null,
		"coords": [476,346,6],
		"noteURL":"http://i.imgur.com/1p8Y7eP.png"
	},
	{
		"name": null,
		"coords": [777,39,6],
		"noteURL":"http://i.imgur.com/1p8Y7eP.png"
	},
	{
		"name": null,
		"coords": [627,110,5],
		"noteURL":"http://i.imgur.com/1p8Y7eP.png"
	},
	{
		"name": null,
		"coords": [629,500,5],
		"noteURL":"http://i.imgur.com/1p8Y7eP.png"
	},
	{
		"name": null,
		"coords": [647,446,5],
		"noteURL":"http://i.imgur.com/1p8Y7eP.png"
	},
	{
		"name": null,
		"coords": [703,767,5],
		"noteURL":"http://i.imgur.com/1p8Y7eP.png"
	},
	{
		"name": null,
		"coords": [394,860,5],
		"noteURL":"http://i.imgur.com/1p8Y7eP.png"
	},
	{
		"name": null,
		"coords": [269,359,5],
		"noteURL":"http://i.imgur.com/1p8Y7eP.png"
	},
	{
		"name": null,
		"coords": [594,14,5],
		"noteURL":"http://i.imgur.com/1p8Y7eP.png"
	},
	{
		"name": null,
		"coords": [761,75,5],
		"noteURL":"http://i.imgur.com/1p8Y7eP.png"
	},
	{
		"name": null,
		"coords": [317,706,5],
		"noteURL":"http://i.imgur.com/1p8Y7eP.png"
	},
	{
		"name": null,
		"coords": [153,767,5],
		"noteURL":"http://i.imgur.com/1p8Y7eP.png"
	},
	{
		"name": null,
		"coords": [486,581,5],
		"noteURL":"http://i.imgur.com/1p8Y7eP.png"
	},
	{
		"name": null,
		"coords": [306,275,5],
		"noteURL":"http://i.imgur.com/1p8Y7eP.png"
	},
	{
		"name": null,
		"coords": [299,255,5],
		"noteURL":"http://i.imgur.com/1p8Y7eP.png"
	},
	{
		"name": null,
		"coords": [346,538,5],
		"noteURL":"http://i.imgur.com/1p8Y7eP.png"
	},
	{
		"name": null,
		"coords": [595,220,5],
		"noteURL":"http://i.imgur.com/1p8Y7eP.png"
	},
	{
		"name": null,
		"coords": [494,185,5],
		"noteURL":"http://i.imgur.com/1p8Y7eP.png"
	},
	{
		"name": null,
		"coords": [224,445,4],
		"noteURL":"http://i.imgur.com/1p8Y7eP.png"
	},
	{
		"name": null,
		"coords": [517,828,4],
		"noteURL":"http://i.imgur.com/1p8Y7eP.png"
	},
	{
		"name": null,
		"coords": [631,160,4],
		"noteURL":"http://i.imgur.com/1p8Y7eP.png"
	},
	{
		"name": null,
		"coords": [450,230,4],
		"noteURL":"http://i.imgur.com/1p8Y7eP.png"
	},
	{
		"name": null,
		"coords": [886,257,4],
		"noteURL":"http://i.imgur.com/1p8Y7eP.png"
	},
	{
		"name": null,
		"coords": [857,153,4],
		"noteURL":"http://i.imgur.com/1p8Y7eP.png"
	},
	{
		"name": null,
		"coords": [536,299,4],
		"noteURL":"http://i.imgur.com/1p8Y7eP.png"
	},
	{
		"name": null,
		"coords": [332,311,4],
		"noteURL":"http://i.imgur.com/1p8Y7eP.png"
	},
	{
		"name": null,
		"coords": [38,322,4],
		"noteURL":"http://i.imgur.com/1p8Y7eP.png"
	},
	{
		"name": null,
		"coords": [330,336,4],
		"noteURL":"http://i.imgur.com/1p8Y7eP.png"
	},
	{
		"name": null,
		"coords": [129,130,4],
		"noteURL":"http://i.imgur.com/1p8Y7eP.png"
	},
	{
		"name": null,
		"coords": [264,370,4],
		"noteURL":"http://i.imgur.com/1p8Y7eP.png"
	},
	{
		"name": null,
		"coords": [525,380,4],
		"noteURL":"http://i.imgur.com/1p8Y7eP.png"
	},
	{
		"name": null,
		"coords": [843,393,4],
		"noteURL":"http://i.imgur.com/1p8Y7eP.png"
	},
	{
		"name": null,
		"coords": [600,402,4],
		"noteURL":"http://i.imgur.com/1p8Y7eP.png"
	},
	{
		"name": null,
		"coords": [906,403,4],
		"noteURL":"http://i.imgur.com/1p8Y7eP.png"
	},
	{
		"name": null,
		"coords": [752,408,4],
		"noteURL":"http://i.imgur.com/1p8Y7eP.png"
	},
	{
		"name": null,
		"coords": [35,123,4],
		"noteURL":"http://i.imgur.com/1p8Y7eP.png"
	},
	{
		"name": null,
		"coords": [712,434,4],
		"noteURL":"http://i.imgur.com/1p8Y7eP.png"
	},
	{
		"name": null,
		"coords": [756,189,4],
		"noteURL":"http://i.imgur.com/1p8Y7eP.png"
	},
	{
		"name": null,
		"coords": [690,22,4],
		"noteURL":"http://i.imgur.com/1p8Y7eP.png"
	},
	{
		"name": null,
		"coords": [762,15,4],
		"noteURL":"http://i.imgur.com/1p8Y7eP.png"
	},
	{
		"name": null,
		"coords": [431,563,4],
		"noteURL":"http://i.imgur.com/1p8Y7eP.png"
	},
	{
		"name": null,
		"coords": [62,566,4],
		"noteURL":"http://i.imgur.com/1p8Y7eP.png"
	},
	{
		"name": null,
		"coords": [288,566,4],
		"noteURL":"http://i.imgur.com/1p8Y7eP.png"
	},
	{
		"name": null,
		"coords": [907,568,4],
		"noteURL":"http://i.imgur.com/1p8Y7eP.png"
	},
	{
		"name": null,
		"coords": [459,71,4],
		"noteURL":"http://i.imgur.com/1p8Y7eP.png"
	},
	{
		"name": null,
		"coords": [331,607,4],
		"noteURL":"http://i.imgur.com/1p8Y7eP.png"
	},
	{
		"name": null,
		"coords": [725,621,4],
		"noteURL":"http://i.imgur.com/1p8Y7eP.png"
	},
	{
		"name": null,
		"coords": [447,59,4],
		"noteURL":"http://i.imgur.com/1p8Y7eP.png"
	},
	{
		"name": null,
		"coords": [16,721,4],
		"noteURL":"http://i.imgur.com/1p8Y7eP.png"
	},
	{
		"name": null,
		"coords": [748,721,4],
		"noteURL":"http://i.imgur.com/1p8Y7eP.png"
	},
	{
		"name": null,
		"coords": [822,57,4],
		"noteURL":"http://i.imgur.com/1p8Y7eP.png"
	},
	{
		"name": null,
		"coords": [369,771,4],
		"noteURL":"http://i.imgur.com/1p8Y7eP.png"
	},
	{
		"name": null,
		"coords": [584,772,4],
		"noteURL":"http://i.imgur.com/1p8Y7eP.png"
	},
	{
		"name": null,
		"coords": [232,772,4],
		"noteURL":"http://i.imgur.com/1p8Y7eP.png"
	},
	{
		"name": null,
		"coords": [141,807,4],
		"noteURL":"http://i.imgur.com/1p8Y7eP.png"
	},
	{
		"name": null,
		"coords": [542,109,3],
		"noteURL":"http://i.imgur.com/1p8Y7eP.png"
	},
	{
		"name": null,
		"coords": [884,322,3],
		"noteURL":"http://i.imgur.com/1p8Y7eP.png"
	},
	{
		"name": null,
		"coords": [456,327,3],
		"noteURL":"http://i.imgur.com/1p8Y7eP.png"
	},
	{
		"name": null,
		"coords": [145,873,3],
		"noteURL":"http://i.imgur.com/1p8Y7eP.png"
	},
	{
		"name": null,
		"coords": [879,330,3],
		"noteURL":"http://i.imgur.com/1p8Y7eP.png"
	},
	{
		"name": null,
		"coords": [210,331,3],
		"noteURL":"http://i.imgur.com/1p8Y7eP.png"
	},
	{
		"name": null,
		"coords": [621,221,3],
		"noteURL":"http://i.imgur.com/1p8Y7eP.png"
	},
	{
		"name": null,
		"coords": [52,341,3],
		"noteURL":"http://i.imgur.com/1p8Y7eP.png"
	},
	{
		"name": null,
		"coords": [670,342,3],
		"noteURL":"http://i.imgur.com/1p8Y7eP.png"
	},
	{
		"name": null,
		"coords": [746,143,3],
		"noteURL":"http://i.imgur.com/1p8Y7eP.png"
	},
	{
		"name": null,
		"coords": [636,138,3],
		"noteURL":"http://i.imgur.com/1p8Y7eP.png"
	},
	{
		"name": null,
		"coords": [288,345,3],
		"noteURL":"http://i.imgur.com/1p8Y7eP.png"
	},
	{
		"name": null,
		"coords": [674,347,3],
		"noteURL":"http://i.imgur.com/1p8Y7eP.png"
	},
	{
		"name": null,
		"coords": [141,352,3],
		"noteURL":"http://i.imgur.com/1p8Y7eP.png"
	},
	{
		"name": null,
		"coords": [715,168,3],
		"noteURL":"http://i.imgur.com/1p8Y7eP.png"
	},
	{
		"name": null,
		"coords": [42,121,3],
		"noteURL":"http://i.imgur.com/1p8Y7eP.png"
	},
	{
		"name": null,
		"coords": [723,360,3],
		"noteURL":"http://i.imgur.com/1p8Y7eP.png"
	},
	{
		"name": null,
		"coords": [769,366,3],
		"noteURL":"http://i.imgur.com/1p8Y7eP.png"
	},
	{
		"name": null,
		"coords": [847,224,3],
		"noteURL":"http://i.imgur.com/1p8Y7eP.png"
	},
	{
		"name": null,
		"coords": [376,376,3],
		"noteURL":"http://i.imgur.com/1p8Y7eP.png"
	},
	{
		"name": null,
		"coords": [633,228,3],
		"noteURL":"http://i.imgur.com/1p8Y7eP.png"
	},
	{
		"name": null,
		"coords": [676,387,3],
		"noteURL":"http://i.imgur.com/1p8Y7eP.png"
	},
	{
		"name": null,
		"coords": [399,186,3],
		"noteURL":"http://i.imgur.com/1p8Y7eP.png"
	},
	{
		"name": null,
		"coords": [872,392,3],
		"noteURL":"http://i.imgur.com/1p8Y7eP.png"
	},
	{
		"name": null,
		"coords": [876,394,3],
		"noteURL":"http://i.imgur.com/1p8Y7eP.png"
	},
	{
		"name": null,
		"coords": [593,396,3],
		"noteURL":"http://i.imgur.com/1p8Y7eP.png"
	},
	{
		"name": null,
		"coords": [748,894,3],
		"noteURL":"http://i.imgur.com/1p8Y7eP.png"
	},
	{
		"name": null,
		"coords": [376,235,3],
		"noteURL":"http://i.imgur.com/1p8Y7eP.png"
	},
	{
		"name": null,
		"coords": [27,403,3],
		"noteURL":"http://i.imgur.com/1p8Y7eP.png"
	},
	{
		"name": null,
		"coords": [690,405,3],
		"noteURL":"http://i.imgur.com/1p8Y7eP.png"
	},
	{
		"name": null,
		"coords": [350,405,3],
		"noteURL":"http://i.imgur.com/1p8Y7eP.png"
	},
	{
		"name": null,
		"coords": [809,875,3],
		"noteURL":"http://i.imgur.com/1p8Y7eP.png"
	},
	{
		"name": null,
		"coords": [613,872,3],
		"noteURL":"http://i.imgur.com/1p8Y7eP.png"
	},
	{
		"name": null,
		"coords": [432,425,3],
		"noteURL":"http://i.imgur.com/1p8Y7eP.png"
	},
	{
		"name": null,
		"coords": [515,244,3],
		"noteURL":"http://i.imgur.com/1p8Y7eP.png"
	},
	{
		"name": null,
		"coords": [774,433,3],
		"noteURL":"http://i.imgur.com/1p8Y7eP.png"
	},
	{
		"name": null,
		"coords": [651,874,3],
		"noteURL":"http://i.imgur.com/1p8Y7eP.png"
	},
	{
		"name": null,
		"coords": [136,435,3],
		"noteURL":"http://i.imgur.com/1p8Y7eP.png"
	},
	{
		"name": null,
		"coords": [354,437,3],
		"noteURL":"http://i.imgur.com/1p8Y7eP.png"
	},
	{
		"name": null,
		"coords": [596,436,3],
		"noteURL":"http://i.imgur.com/1p8Y7eP.png"
	},
	{
		"name": null,
		"coords": [140,874,3],
		"noteURL":"http://i.imgur.com/1p8Y7eP.png"
	},
	{
		"name": null,
		"coords": [749,111,3],
		"noteURL":"http://i.imgur.com/1p8Y7eP.png"
	},
	{
		"name": null,
		"coords": [873,447,3],
		"noteURL":"http://i.imgur.com/1p8Y7eP.png"
	},
	{
		"name": null,
		"coords": [784,252,3],
		"noteURL":"http://i.imgur.com/1p8Y7eP.png"
	},
	{
		"name": null,
		"coords": [516,157,3],
		"noteURL":"http://i.imgur.com/1p8Y7eP.png"
	},
	{
		"name": null,
		"coords": [197,458,3],
		"noteURL":"http://i.imgur.com/1p8Y7eP.png"
	},
	{
		"name": null,
		"coords": [173,463,3],
		"noteURL":"http://i.imgur.com/1p8Y7eP.png"
	},
	{
		"name": null,
		"coords": [688,463,3],
		"noteURL":"http://i.imgur.com/1p8Y7eP.png"
	},
	{
		"name": null,
		"coords": [720,470,3],
		"noteURL":"http://i.imgur.com/1p8Y7eP.png"
	},
	{
		"name": null,
		"coords": [65,474,3],
		"noteURL":"http://i.imgur.com/1p8Y7eP.png"
	},
	{
		"name": null,
		"coords": [679,473,3],
		"noteURL":"http://i.imgur.com/1p8Y7eP.png"
	},
	{
		"name": null,
		"coords": [464,474,3],
		"noteURL":"http://i.imgur.com/1p8Y7eP.png"
	},
	{
		"name": null,
		"coords": [296,475,3],
		"noteURL":"http://i.imgur.com/1p8Y7eP.png"
	},
	{
		"name": null,
		"coords": [430,475,3],
		"noteURL":"http://i.imgur.com/1p8Y7eP.png"
	},
	{
		"name": null,
		"coords": [753,476,3],
		"noteURL":"http://i.imgur.com/1p8Y7eP.png"
	},
	{
		"name": null,
		"coords": [609,484,3],
		"noteURL":"http://i.imgur.com/1p8Y7eP.png"
	},
	{
		"name": null,
		"coords": [673,483,3],
		"noteURL":"http://i.imgur.com/1p8Y7eP.png"
	},
	{
		"name": null,
		"coords": [635,485,3],
		"noteURL":"http://i.imgur.com/1p8Y7eP.png"
	},
	{
		"name": null,
		"coords": [629,485,3],
		"noteURL":"http://i.imgur.com/1p8Y7eP.png"
	},
	{
		"name": null,
		"coords": [860,492,3],
		"noteURL":"http://i.imgur.com/1p8Y7eP.png"
	},
	{
		"name": null,
		"coords": [224,499,3],
		"noteURL":"http://i.imgur.com/1p8Y7eP.png"
	},
	{
		"name": null,
		"coords": [256,498,3],
		"noteURL":"http://i.imgur.com/1p8Y7eP.png"
	},
	{
		"name": null,
		"coords": [523,180,3],
		"noteURL":"http://i.imgur.com/1p8Y7eP.png"
	},
	{
		"name": null,
		"coords": [569,501,3],
		"noteURL":"http://i.imgur.com/1p8Y7eP.png"
	},
	{
		"name": null,
		"coords": [354,508,3],
		"noteURL":"http://i.imgur.com/1p8Y7eP.png"
	},
	{
		"name": null,
		"coords": [56,512,3],
		"noteURL":"http://i.imgur.com/1p8Y7eP.png"
	},
	{
		"name": null,
		"coords": [294,520,3],
		"noteURL":"http://i.imgur.com/1p8Y7eP.png"
	},
	{
		"name": null,
		"coords": [450,524,3],
		"noteURL":"http://i.imgur.com/1p8Y7eP.png"
	},
	{
		"name": null,
		"coords": [520,523,3],
		"noteURL":"http://i.imgur.com/1p8Y7eP.png"
	},
	{
		"name": null,
		"coords": [100,865,3],
		"noteURL":"http://i.imgur.com/1p8Y7eP.png"
	},
	{
		"name": null,
		"coords": [472,107,3],
		"noteURL":"http://i.imgur.com/1p8Y7eP.png"
	},
	{
		"name": null,
		"coords": [581,539,3],
		"noteURL":"http://i.imgur.com/1p8Y7eP.png"
	},
	{
		"name": null,
		"coords": [545,540,3],
		"noteURL":"http://i.imgur.com/1p8Y7eP.png"
	},
	{
		"name": null,
		"coords": [335,542,3],
		"noteURL":"http://i.imgur.com/1p8Y7eP.png"
	},
	{
		"name": null,
		"coords": [403,174,3],
		"noteURL":"http://i.imgur.com/1p8Y7eP.png"
	},
	{
		"name": null,
		"coords": [249,872,3],
		"noteURL":"http://i.imgur.com/1p8Y7eP.png"
	},
	{
		"name": null,
		"coords": [312,564,3],
		"noteURL":"http://i.imgur.com/1p8Y7eP.png"
	},
	{
		"name": null,
		"coords": [404,211,3],
		"noteURL":"http://i.imgur.com/1p8Y7eP.png"
	},
	{
		"name": null,
		"coords": [452,565,3],
		"noteURL":"http://i.imgur.com/1p8Y7eP.png"
	},
	{
		"name": null,
		"coords": [692,277,3],
		"noteURL":"http://i.imgur.com/1p8Y7eP.png"
	},
	{
		"name": null,
		"coords": [381,575,3],
		"noteURL":"http://i.imgur.com/1p8Y7eP.png"
	},
	{
		"name": null,
		"coords": [605,858,3],
		"noteURL":"http://i.imgur.com/1p8Y7eP.png"
	},
	{
		"name": null,
		"coords": [822,105,3],
		"noteURL":"http://i.imgur.com/1p8Y7eP.png"
	},
	{
		"name": null,
		"coords": [775,81,3],
		"noteURL":"http://i.imgur.com/1p8Y7eP.png"
	},
	{
		"name": null,
		"coords": [34,581,3],
		"noteURL":"http://i.imgur.com/1p8Y7eP.png"
	},
	{
		"name": null,
		"coords": [635,583,3],
		"noteURL":"http://i.imgur.com/1p8Y7eP.png"
	},
	{
		"name": null,
		"coords": [787,584,3],
		"noteURL":"http://i.imgur.com/1p8Y7eP.png"
	},
	{
		"name": null,
		"coords": [554,281,3],
		"noteURL":"http://i.imgur.com/1p8Y7eP.png"
	},
	{
		"name": null,
		"coords": [470,284,3],
		"noteURL":"http://i.imgur.com/1p8Y7eP.png"
	},
	{
		"name": null,
		"coords": [838,608,3],
		"noteURL":"http://i.imgur.com/1p8Y7eP.png"
	},
	{
		"name": null,
		"coords": [901,616,3],
		"noteURL":"http://i.imgur.com/1p8Y7eP.png"
	},
	{
		"name": null,
		"coords": [233,619,3],
		"noteURL":"http://i.imgur.com/1p8Y7eP.png"
	},
	{
		"name": null,
		"coords": [428,68,3],
		"noteURL":"http://i.imgur.com/1p8Y7eP.png"
	},
	{
		"name": null,
		"coords": [611,296,3],
		"noteURL":"http://i.imgur.com/1p8Y7eP.png"
	},
	{
		"name": null,
		"coords": [518,623,3],
		"noteURL":"http://i.imgur.com/1p8Y7eP.png"
	},
	{
		"name": null,
		"coords": [352,627,3],
		"noteURL":"http://i.imgur.com/1p8Y7eP.png"
	},
	{
		"name": null,
		"coords": [157,630,3],
		"noteURL":"http://i.imgur.com/1p8Y7eP.png"
	},
	{
		"name": null,
		"coords": [782,635,3],
		"noteURL":"http://i.imgur.com/1p8Y7eP.png"
	},
	{
		"name": null,
		"coords": [473,642,3],
		"noteURL":"http://i.imgur.com/1p8Y7eP.png"
	},
	{
		"name": null,
		"coords": [766,651,3],
		"noteURL":"http://i.imgur.com/1p8Y7eP.png"
	},
	{
		"name": null,
		"coords": [55,61,3],
		"noteURL":"http://i.imgur.com/1p8Y7eP.png"
	},
	{
		"name": null,
		"coords": [304,660,3],
		"noteURL":"http://i.imgur.com/1p8Y7eP.png"
	},
	{
		"name": null,
		"coords": [749,661,3],
		"noteURL":"http://i.imgur.com/1p8Y7eP.png"
	},
	{
		"name": null,
		"coords": [826,662,3],
		"noteURL":"http://i.imgur.com/1p8Y7eP.png"
	},
	{
		"name": null,
		"coords": [81,664,3],
		"noteURL":"http://i.imgur.com/1p8Y7eP.png"
	},
	{
		"name": null,
		"coords": [454,667,3],
		"noteURL":"http://i.imgur.com/1p8Y7eP.png"
	},
	{
		"name": null,
		"coords": [564,678,3],
		"noteURL":"http://i.imgur.com/1p8Y7eP.png"
	},
	{
		"name": null,
		"coords": [674,677,3],
		"noteURL":"http://i.imgur.com/1p8Y7eP.png"
	},
	{
		"name": null,
		"coords": [639,60,3],
		"noteURL":"http://i.imgur.com/1p8Y7eP.png"
	},
	{
		"name": null,
		"coords": [453,680,3],
		"noteURL":"http://i.imgur.com/1p8Y7eP.png"
	},
	{
		"name": null,
		"coords": [179,681,3],
		"noteURL":"http://i.imgur.com/1p8Y7eP.png"
	},
	{
		"name": null,
		"coords": [351,688,3],
		"noteURL":"http://i.imgur.com/1p8Y7eP.png"
	},
	{
		"name": null,
		"coords": [701,697,3],
		"noteURL":"http://i.imgur.com/1p8Y7eP.png"
	},
	{
		"name": null,
		"coords": [12,699,3],
		"noteURL":"http://i.imgur.com/1p8Y7eP.png"
	},
	{
		"name": null,
		"coords": [427,699,3],
		"noteURL":"http://i.imgur.com/1p8Y7eP.png"
	},
	{
		"name": null,
		"coords": [795,699,3],
		"noteURL":"http://i.imgur.com/1p8Y7eP.png"
	},
	{
		"name": null,
		"coords": [672,702,3],
		"noteURL":"http://i.imgur.com/1p8Y7eP.png"
	},
	{
		"name": null,
		"coords": [865,215,3],
		"noteURL":"http://i.imgur.com/1p8Y7eP.png"
	},
	{
		"name": null,
		"coords": [410,707,3],
		"noteURL":"http://i.imgur.com/1p8Y7eP.png"
	},
	{
		"name": null,
		"coords": [461,706,3],
		"noteURL":"http://i.imgur.com/1p8Y7eP.png"
	},
	{
		"name": null,
		"coords": [377,711,3],
		"noteURL":"http://i.imgur.com/1p8Y7eP.png"
	},
	{
		"name": null,
		"coords": [742,296,3],
		"noteURL":"http://i.imgur.com/1p8Y7eP.png"
	},
	{
		"name": null,
		"coords": [343,301,3],
		"noteURL":"http://i.imgur.com/1p8Y7eP.png"
	},
	{
		"name": null,
		"coords": [715,721,3],
		"noteURL":"http://i.imgur.com/1p8Y7eP.png"
	},
	{
		"name": null,
		"coords": [120,722,3],
		"noteURL":"http://i.imgur.com/1p8Y7eP.png"
	},
	{
		"name": null,
		"coords": [257,730,3],
		"noteURL":"http://i.imgur.com/1p8Y7eP.png"
	},
	{
		"name": null,
		"coords": [127,303,3],
		"noteURL":"http://i.imgur.com/1p8Y7eP.png"
	},
	{
		"name": null,
		"coords": [852,734,3],
		"noteURL":"http://i.imgur.com/1p8Y7eP.png"
	},
	{
		"name": null,
		"coords": [381,55,3],
		"noteURL":"http://i.imgur.com/1p8Y7eP.png"
	},
	{
		"name": null,
		"coords": [223,748,3],
		"noteURL":"http://i.imgur.com/1p8Y7eP.png"
	},
	{
		"name": null,
		"coords": [149,751,3],
		"noteURL":"http://i.imgur.com/1p8Y7eP.png"
	},
	{
		"name": null,
		"coords": [611,751,3],
		"noteURL":"http://i.imgur.com/1p8Y7eP.png"
	},
	{
		"name": null,
		"coords": [355,759,3],
		"noteURL":"http://i.imgur.com/1p8Y7eP.png"
	},
	{
		"name": null,
		"coords": [274,44,3],
		"noteURL":"http://i.imgur.com/1p8Y7eP.png"
	},
	{
		"name": null,
		"coords": [900,763,3],
		"noteURL":"http://i.imgur.com/1p8Y7eP.png"
	},
	{
		"name": null,
		"coords": [68,41,3],
		"noteURL":"http://i.imgur.com/1p8Y7eP.png"
	},
	{
		"name": null,
		"coords": [96,905,3],
		"noteURL":"http://i.imgur.com/1p8Y7eP.png"
	},
	{
		"name": null,
		"coords": [605,767,3],
		"noteURL":"http://i.imgur.com/1p8Y7eP.png"
	},
	{
		"name": null,
		"coords": [677,308,3],
		"noteURL":"http://i.imgur.com/1p8Y7eP.png"
	},
	{
		"name": null,
		"coords": [51,310,3],
		"noteURL":"http://i.imgur.com/1p8Y7eP.png"
	},
	{
		"name": null,
		"coords": [655,770,3],
		"noteURL":"http://i.imgur.com/1p8Y7eP.png"
	},
	{
		"name": null,
		"coords": [668,161,3],
		"noteURL":"http://i.imgur.com/1p8Y7eP.png"
	},
	{
		"name": null,
		"coords": [281,854,3],
		"noteURL":"http://i.imgur.com/1p8Y7eP.png"
	},
	{
		"name": null,
		"coords": [207,36,3],
		"noteURL":"http://i.imgur.com/1p8Y7eP.png"
	},
	{
		"name": null,
		"coords": [439,792,3],
		"noteURL":"http://i.imgur.com/1p8Y7eP.png"
	},
	{
		"name": null,
		"coords": [25,793,3],
		"noteURL":"http://i.imgur.com/1p8Y7eP.png"
	},
	{
		"name": null,
		"coords": [638,794,3],
		"noteURL":"http://i.imgur.com/1p8Y7eP.png"
	},
	{
		"name": null,
		"coords": [494,795,3],
		"noteURL":"http://i.imgur.com/1p8Y7eP.png"
	},
	{
		"name": null,
		"coords": [188,796,3],
		"noteURL":"http://i.imgur.com/1p8Y7eP.png"
	},
	{
		"name": null,
		"coords": [697,796,3],
		"noteURL":"http://i.imgur.com/1p8Y7eP.png"
	},
	{
		"name": null,
		"coords": [251,319,3],
		"noteURL":"http://i.imgur.com/1p8Y7eP.png"
	},
	{
		"name": null,
		"coords": [286,814,3],
		"noteURL":"http://i.imgur.com/1p8Y7eP.png"
	},
	{
		"name": null,
		"coords": [560,816,3],
		"noteURL":"http://i.imgur.com/1p8Y7eP.png"
	},
	{
		"name": null,
		"coords": [158,819,3],
		"noteURL":"http://i.imgur.com/1p8Y7eP.png"
	},
	{
		"name": null,
		"coords": [768,820,3],
		"noteURL":"http://i.imgur.com/1p8Y7eP.png"
	},
	{
		"name": null,
		"coords": [904,822,3],
		"noteURL":"http://i.imgur.com/1p8Y7eP.png"
	},
	{
		"name": null,
		"coords": [409,218,3],
		"noteURL":"http://i.imgur.com/1p8Y7eP.png"
	},
	{
		"name": null,
		"coords": [795,840,3],
		"noteURL":"http://i.imgur.com/1p8Y7eP.png"
	},
	{
		"name": null,
		"coords": [416,833,3],
		"noteURL":"http://i.imgur.com/1p8Y7eP.png"
	},
	{
		"name": null,
		"coords": [355,839,3],
		"noteURL":"http://i.imgur.com/1p8Y7eP.png"
	},
	{
		"name": null,
		"coords": [470,452,3],
		"noteURL":"http://i.imgur.com/1p8Y7eP.png"
	},
	{
		"name": null,
		"coords": [569,205,2],
		"noteURL":"http://i.imgur.com/1p8Y7eP.png"
	},
	{
		"name": null,
		"coords": [662,304,2],
		"noteURL":"http://i.imgur.com/1p8Y7eP.png"
	},
	{
		"name": null,
		"coords": [693,80,2],
		"noteURL":"http://i.imgur.com/1p8Y7eP.png"
	},
	{
		"name": null,
		"coords": [848,209,2],
		"noteURL":"http://i.imgur.com/1p8Y7eP.png"
	},
	{
		"name": null,
		"coords": [548,39,2],
		"noteURL":"http://i.imgur.com/1p8Y7eP.png"
	},
	{
		"name": null,
		"coords": [190,440,2],
		"noteURL":"http://i.imgur.com/1p8Y7eP.png"
	},
	{
		"name": null,
		"coords": [136,441,2],
		"noteURL":"http://i.imgur.com/1p8Y7eP.png"
	},
	{
		"name": null,
		"coords": [649,310,2],
		"noteURL":"http://i.imgur.com/1p8Y7eP.png"
	},
	{
		"name": null,
		"coords": [585,855,2],
		"noteURL":"http://i.imgur.com/1p8Y7eP.png"
	},
	{
		"name": null,
		"coords": [502,214,2],
		"noteURL":"http://i.imgur.com/1p8Y7eP.png"
	},
	{
		"name": null,
		"coords": [571,648,2],
		"noteURL":"http://i.imgur.com/1p8Y7eP.png"
	},
	{
		"name": null,
		"coords": [656,647,2],
		"noteURL":"http://i.imgur.com/1p8Y7eP.png"
	},
	{
		"name": null,
		"coords": [524,216,2],
		"noteURL":"http://i.imgur.com/1p8Y7eP.png"
	},
	{
		"name": null,
		"coords": [477,449,2],
		"noteURL":"http://i.imgur.com/1p8Y7eP.png"
	},
	{
		"name": null,
		"coords": [609,138,2],
		"noteURL":"http://i.imgur.com/1p8Y7eP.png"
	},
	{
		"name": null,
		"coords": [294,325,2],
		"noteURL":"http://i.imgur.com/1p8Y7eP.png"
	},
	{
		"name": null,
		"coords": [861,101,2],
		"noteURL":"http://i.imgur.com/1p8Y7eP.png"
	},
	{
		"name": null,
		"coords": [652,28,2],
		"noteURL":"http://i.imgur.com/1p8Y7eP.png"
	},
	{
		"name": null,
		"coords": [685,663,2],
		"noteURL":"http://i.imgur.com/1p8Y7eP.png"
	},
	{
		"name": null,
		"coords": [531,145,2],
		"noteURL":"http://i.imgur.com/1p8Y7eP.png"
	},
	{
		"name": null,
		"coords": [420,224,2],
		"noteURL":"http://i.imgur.com/1p8Y7eP.png"
	},
	{
		"name": null,
		"coords": [343,146,2],
		"noteURL":"http://i.imgur.com/1p8Y7eP.png"
	},
	{
		"name": null,
		"coords": [890,869,2],
		"noteURL":"http://i.imgur.com/1p8Y7eP.png"
	},
	{
		"name": null,
		"coords": [220,336,2],
		"noteURL":"http://i.imgur.com/1p8Y7eP.png"
	},
	{
		"name": null,
		"coords": [376,40,2],
		"noteURL":"http://i.imgur.com/1p8Y7eP.png"
	},
	{
		"name": null,
		"coords": [570,684,2],
		"noteURL":"http://i.imgur.com/1p8Y7eP.png"
	},
	{
		"name": null,
		"coords": [771,17,2],
		"noteURL":"http://i.imgur.com/1p8Y7eP.png"
	},
	{
		"name": null,
		"coords": [679,695,2],
		"noteURL":"http://i.imgur.com/1p8Y7eP.png"
	},
	{
		"name": null,
		"coords": [843,228,2],
		"noteURL":"http://i.imgur.com/1p8Y7eP.png"
	},
	{
		"name": null,
		"coords": [771,152,2],
		"noteURL":"http://i.imgur.com/1p8Y7eP.png"
	},
	{
		"name": null,
		"coords": [834,478,2],
		"noteURL":"http://i.imgur.com/1p8Y7eP.png"
	},
	{
		"name": null,
		"coords": [665,479,2],
		"noteURL":"http://i.imgur.com/1p8Y7eP.png"
	},
	{
		"name": null,
		"coords": [903,865,2],
		"noteURL":"http://i.imgur.com/1p8Y7eP.png"
	},
	{
		"name": null,
		"coords": [562,154,2],
		"noteURL":"http://i.imgur.com/1p8Y7eP.png"
	},
	{
		"name": null,
		"coords": [735,237,2],
		"noteURL":"http://i.imgur.com/1p8Y7eP.png"
	},
	{
		"name": null,
		"coords": [802,44,2],
		"noteURL":"http://i.imgur.com/1p8Y7eP.png"
	},
	{
		"name": null,
		"coords": [732,707,2],
		"noteURL":"http://i.imgur.com/1p8Y7eP.png"
	},
	{
		"name": null,
		"coords": [690,709,2],
		"noteURL":"http://i.imgur.com/1p8Y7eP.png"
	},
	{
		"name": null,
		"coords": [300,711,2],
		"noteURL":"http://i.imgur.com/1p8Y7eP.png"
	},
	{
		"name": null,
		"coords": [679,240,2],
		"noteURL":"http://i.imgur.com/1p8Y7eP.png"
	},
	{
		"name": null,
		"coords": [382,711,2],
		"noteURL":"http://i.imgur.com/1p8Y7eP.png"
	},
	{
		"name": null,
		"coords": [495,711,2],
		"noteURL":"http://i.imgur.com/1p8Y7eP.png"
	},
	{
		"name": null,
		"coords": [25,716,2],
		"noteURL":"http://i.imgur.com/1p8Y7eP.png"
	},
	{
		"name": null,
		"coords": [549,489,2],
		"noteURL":"http://i.imgur.com/1p8Y7eP.png"
	},
	{
		"name": null,
		"coords": [679,155,2],
		"noteURL":"http://i.imgur.com/1p8Y7eP.png"
	},
	{
		"name": null,
		"coords": [158,498,2],
		"noteURL":"http://i.imgur.com/1p8Y7eP.png"
	},
	{
		"name": null,
		"coords": [304,906,2],
		"noteURL":"http://i.imgur.com/1p8Y7eP.png"
	},
	{
		"name": null,
		"coords": [667,725,2],
		"noteURL":"http://i.imgur.com/1p8Y7eP.png"
	},
	{
		"name": null,
		"coords": [569,360,2],
		"noteURL":"http://i.imgur.com/1p8Y7eP.png"
	},
	{
		"name": null,
		"coords": [431,361,2],
		"noteURL":"http://i.imgur.com/1p8Y7eP.png"
	},
	{
		"name": null,
		"coords": [250,363,2],
		"noteURL":"http://i.imgur.com/1p8Y7eP.png"
	},
	{
		"name": null,
		"coords": [435,736,2],
		"noteURL":"http://i.imgur.com/1p8Y7eP.png"
	},
	{
		"name": null,
		"coords": [604,363,2],
		"noteURL":"http://i.imgur.com/1p8Y7eP.png"
	},
	{
		"name": null,
		"coords": [21,118,2],
		"noteURL":"http://i.imgur.com/1p8Y7eP.png"
	},
	{
		"name": null,
		"coords": [405,748,2],
		"noteURL":"http://i.imgur.com/1p8Y7eP.png"
	},
	{
		"name": null,
		"coords": [744,903,2],
		"noteURL":"http://i.imgur.com/1p8Y7eP.png"
	},
	{
		"name": null,
		"coords": [805,894,2],
		"noteURL":"http://i.imgur.com/1p8Y7eP.png"
	},
	{
		"name": null,
		"coords": [519,855,2],
		"noteURL":"http://i.imgur.com/1p8Y7eP.png"
	},
	{
		"name": null,
		"coords": [196,375,2],
		"noteURL":"http://i.imgur.com/1p8Y7eP.png"
	},
	{
		"name": null,
		"coords": [357,525,2],
		"noteURL":"http://i.imgur.com/1p8Y7eP.png"
	},
	{
		"name": null,
		"coords": [512,763,2],
		"noteURL":"http://i.imgur.com/1p8Y7eP.png"
	},
	{
		"name": null,
		"coords": [303,24,2],
		"noteURL":"http://i.imgur.com/1p8Y7eP.png"
	},
	{
		"name": null,
		"coords": [32,863,2],
		"noteURL":"http://i.imgur.com/1p8Y7eP.png"
	},
	{
		"name": null,
		"coords": [210,385,2],
		"noteURL":"http://i.imgur.com/1p8Y7eP.png"
	},
	{
		"name": null,
		"coords": [802,257,2],
		"noteURL":"http://i.imgur.com/1p8Y7eP.png"
	},
	{
		"name": null,
		"coords": [668,767,2],
		"noteURL":"http://i.imgur.com/1p8Y7eP.png"
	},
	{
		"name": null,
		"coords": [626,263,2],
		"noteURL":"http://i.imgur.com/1p8Y7eP.png"
	},
	{
		"name": null,
		"coords": [290,122,2],
		"noteURL":"http://i.imgur.com/1p8Y7eP.png"
	},
	{
		"name": null,
		"coords": [236,552,2],
		"noteURL":"http://i.imgur.com/1p8Y7eP.png"
	},
	{
		"name": null,
		"coords": [573,269,2],
		"noteURL":"http://i.imgur.com/1p8Y7eP.png"
	},
	{
		"name": null,
		"coords": [26,562,2],
		"noteURL":"http://i.imgur.com/1p8Y7eP.png"
	},
	{
		"name": null,
		"coords": [396,783,2],
		"noteURL":"http://i.imgur.com/1p8Y7eP.png"
	},
	{
		"name": null,
		"coords": [23,394,2],
		"noteURL":"http://i.imgur.com/1p8Y7eP.png"
	},
	{
		"name": null,
		"coords": [498,396,2],
		"noteURL":"http://i.imgur.com/1p8Y7eP.png"
	},
	{
		"name": null,
		"coords": [797,791,2],
		"noteURL":"http://i.imgur.com/1p8Y7eP.png"
	},
	{
		"name": null,
		"coords": [497,270,2],
		"noteURL":"http://i.imgur.com/1p8Y7eP.png"
	},
	{
		"name": null,
		"coords": [17,180,2],
		"noteURL":"http://i.imgur.com/1p8Y7eP.png"
	},
	{
		"name": null,
		"coords": [281,401,2],
		"noteURL":"http://i.imgur.com/1p8Y7eP.png"
	},
	{
		"name": null,
		"coords": [454,569,2],
		"noteURL":"http://i.imgur.com/1p8Y7eP.png"
	},
	{
		"name": null,
		"coords": [167,180,2],
		"noteURL":"http://i.imgur.com/1p8Y7eP.png"
	},
	{
		"name": null,
		"coords": [711,795,2],
		"noteURL":"http://i.imgur.com/1p8Y7eP.png"
	},
	{
		"name": null,
		"coords": [548,803,2],
		"noteURL":"http://i.imgur.com/1p8Y7eP.png"
	},
	{
		"name": null,
		"coords": [568,803,2],
		"noteURL":"http://i.imgur.com/1p8Y7eP.png"
	},
	{
		"name": null,
		"coords": [626,573,2],
		"noteURL":"http://i.imgur.com/1p8Y7eP.png"
	},
	{
		"name": null,
		"coords": [339,127,2],
		"noteURL":"http://i.imgur.com/1p8Y7eP.png"
	},
	{
		"name": null,
		"coords": [144,52,2],
		"noteURL":"http://i.imgur.com/1p8Y7eP.png"
	},
	{
		"name": null,
		"coords": [147,136,2],
		"noteURL":"http://i.imgur.com/1p8Y7eP.png"
	},
	{
		"name": null,
		"coords": [701,189,2],
		"noteURL":"http://i.imgur.com/1p8Y7eP.png"
	},
	{
		"name": null,
		"coords": [768,581,2],
		"noteURL":"http://i.imgur.com/1p8Y7eP.png"
	},
	{
		"name": null,
		"coords": [539,409,2],
		"noteURL":"http://i.imgur.com/1p8Y7eP.png"
	},
	{
		"name": null,
		"coords": [864,191,2],
		"noteURL":"http://i.imgur.com/1p8Y7eP.png"
	},
	{
		"name": null,
		"coords": [724,198,2],
		"noteURL":"http://i.imgur.com/1p8Y7eP.png"
	},
	{
		"name": null,
		"coords": [209,836,2],
		"noteURL":"http://i.imgur.com/1p8Y7eP.png"
	},
	{
		"name": null,
		"coords": [400,301,2],
		"noteURL":"http://i.imgur.com/1p8Y7eP.png"
	},
	{
		"name": null,
		"coords": [225,430,2],
		"noteURL":"http://i.imgur.com/1p8Y7eP.png"
	},
	{
		"name": null,
		"coords": [358,456,2],
		"noteURL":"http://i.imgur.com/1p8Y7eP.png"
	},
	{
		"name": null,
		"coords": [111,828,1],
		"noteURL":"http://i.imgur.com/1p8Y7eP.png"
	},
	{
		"name": null,
		"coords": [852,752,1],
		"noteURL":"http://i.imgur.com/1p8Y7eP.png"
	},
	{
		"name": null,
		"coords": [72,638,1],
		"noteURL":"http://i.imgur.com/1p8Y7eP.png"
	},
	{
		"name": null,
		"coords": [399,618,1],
		"noteURL":"http://i.imgur.com/1p8Y7eP.png"
	},
	{
		"name": null,
		"coords": [216,573,1],
		"noteURL":"http://i.imgur.com/1p8Y7eP.png"
	},
	{
		"name": null,
		"coords": [294,532,1],
		"noteURL":"http://i.imgur.com/1p8Y7eP.png"
	},
	{
		"name": null,
		"coords": [506,525,1],
		"noteURL":"http://i.imgur.com/1p8Y7eP.png"
	},
	{
		"name": null,
		"coords": [66,481,1],
		"noteURL":"http://i.imgur.com/1p8Y7eP.png"
	},
	{
		"name": null,
		"coords": [227,471,1],
		"noteURL":"http://i.imgur.com/1p8Y7eP.png"
	},
	{
		"name": null,
		"coords": [565,419,1],
		"noteURL":"http://i.imgur.com/1p8Y7eP.png"
	},
	{
		"name": null,
		"coords": [775,778,1],
		"noteURL":"http://i.imgur.com/1p8Y7eP.png"
	},
	{
		"name": null,
		"coords": [568,267,1],
		"noteURL":"http://i.imgur.com/1p8Y7eP.png"
	},
	{
		"name": null,
		"coords": [728,249,1],
		"noteURL":"http://i.imgur.com/1p8Y7eP.png"
	},
	{
		"name": null,
		"coords": [737,242,1],
		"noteURL":"http://i.imgur.com/1p8Y7eP.png"
	},
	{
		"name": null,
		"coords": [621,237,1],
		"noteURL":"http://i.imgur.com/1p8Y7eP.png"
	},
	{
		"name": null,
		"coords": [892,227,1],
		"noteURL":"http://i.imgur.com/1p8Y7eP.png"
	},
	{
		"name": null,
		"coords": [745,168,1],
		"noteURL":"http://i.imgur.com/1p8Y7eP.png"
	},
	{
		"name": null,
		"coords": [129,50,1],
		"noteURL":"http://i.imgur.com/1p8Y7eP.png"
	},
	{
		"name": null,
		"coords": [405,49,1],
		"noteURL":"http://i.imgur.com/1p8Y7eP.png"
	},
	{
		"name": null,
		"coords": [478,33,1],
		"noteURL":"http://i.imgur.com/1p8Y7eP.png"
	},
	{
		"name": null,
		"coords": [197,326,1],
		"noteURL":"http://i.imgur.com/1p8Y7eP.png"
	}
]